[{
  "_id": {
    "$oid": "64f003354f1f72c9d66e8a1d"
  },
  "name": "Dr. Alice Johnson",
  "email": "alicejohnson@example.com",
  "phone": "1234567890",
  "experience_years": 10,
  "mentee_count": 20
},
{
  "_id": {
    "$oid": "64f003354f1f72c9d66e8a24"
  },
  "name": "Mr. Bob Smith",
  "email": "bobsmith@example.com",
  "phone": "0987654321",
  "experience_years": 8,
  "mentee_count": 18
},
{
  "_id": {
    "$oid": "64f003354f1f72c9d66e8a2d"
  },
  "name": "Ms. Carol Davis",
  "email": "caroldavis@example.com",
  "phone": "1122334455",
  "experience_years": 5,
  "mentee_count": 12
},
{
  "_id": {
    "$oid": "64f003354f1f72c9d66e8a3d"
  },
  "name": "Dr. David Brown",
  "email": "davidbrown@example.com",
  "phone": "2233445566",
  "experience_years": 15,
  "mentee_count": 25
},
{
  "_id": {
    "$oid": "64f003354f1f72c9d66e8a44"
  },
  "name": "Ms. Emily Wilson",
  "email": "emilywilson@example.com",
  "phone": "3344556677",
  "experience_years": 7,
  "mentee_count": 14
},
{
  "_id": {
    "$oid": "64f003354f1f72c9d66e8a51"
  },
  "name": "Mr. Frank Lewis",
  "email": "franklewis@example.com",
  "phone": "4455667788",
  "experience_years": 6,
  "mentee_count": 13
},
{
  "_id": {
    "$oid": "64f003354f1f72c9d66e8a61"
  },
  "name": "Dr. Grace Lee",
  "email": "gracelee@example.com",
  "phone": "5566778899",
  "experience_years": 12,
  "mentee_count": 22
},
{
  "_id": {
    "$oid": "64f003354f1f72c9d66e8a71"
  },
  "name": "Mr. Henry Walker",
  "email": "henrywalker@example.com",
  "phone": "6677889900",
  "experience_years": 9,
  "mentee_count": 16
},
{
  "_id": {
    "$oid": "64f003354f1f72c9d66e8a82"
  },
  "name": "Ms. Irene Scott",
  "email": "irenescott@example.com",
  "phone": "7788990011",
  "experience_years": 11,
  "mentee_count": 19
},
{
  "_id": {
    "$oid": "64f003354f1f72c9d66e8a91"
  },
  "name": "Dr. Jack Harris",
  "email": "jackharris@example.com",
  "phone": "8899001122",
  "experience_years": 13,
  "mentee_count": 21
}]